chiropy/__init__.py
chiropy/ginp.py
chiropy/gout.py
chiropy/main.py
chiropy/assets/Arial.ttf
chiropy/lib/__init__.py
chiropy/lib/calculator.py
chiropy/lib/geometry.py
chiropy/lib/io.py
chiropy/lib/visualizer.py
chiropy-1.0.6.dist-info/LICENSE
chiropy-1.0.6.dist-info/METADATA
chiropy-1.0.6.dist-info/WHEEL
chiropy-1.0.6.dist-info/entry_points.txt
chiropy-1.0.6.dist-info/top_level.txt
chiropy-1.0.6.dist-info/RECORD
