Metadata-Version: 2.1
Name: chiropy
Version: 1.0.6
Summary: CHIROpy is a Gaussian binding tool for analyze chiroptical properties.
Home-page: https://github.com/s-inoue0108/chiropy
Author: Shota Inoue
License: MIT
Requires-Python: >= 3.10, < 3.12
License-File: LICENSE
Requires-Dist: numpy <=1.26.4,>=1.25.2
Requires-Dist: rdkit >=2023.9.6
Requires-Dist: openbabel-wheel ==3.1.1.22
Requires-Dist: networkx <=3.3,>=3.0
Requires-Dist: matplotlib >=3.10.0
